[{"rls":true,"tbl":"_asia_api_staging","force":false},{"rls":false,"tbl":"_backup_20260425_tabela_preco_gravacao_oficial_faixa","force":false},{"rls":false,"tbl":"_backup_20260425_tecnicas_gravacao","force":false},{"rls":false,"tbl":"_backup_guardachuva_setup_20260425","force":false},{"rls":false,"tbl":"_backup_plaquinha_sugestao_20260425","force":false},{"rls":false,"tbl":"_backup_silk_ajustes_20260426","force":false},{"rls":false,"tbl":"_backup_unif_funcoes_20260425","force":false},{"rls":false,"tbl":"_backup_unif_funcoes_f3_20260425","force":false},{"rls":false,"tbl":"_backup_unif_limpeza_fatmin_20260425","force":false},{"rls":false,"tbl":"_backup_unif_setup_fatmin_20260425","force":false},{"rls":false,"tbl":"_backup_unif_setup_fatmin_faixa_20260425","force":false},{"rls":true,"tbl":"_unif_pending_log","force":false},{"rls":true,"tbl":"_unif_settings_arquivo","force":false},{"rls":true,"tbl":"admin_audit_log","force":false},{"rls":true,"tbl":"ai_description_queue","force":false},{"rls":true,"tbl":"ai_function_routing","force":false},{"rls":true,"tbl":"ai_models","force":false},{"rls":true,"tbl":"ai_provider_quotas","force":false},{"rls":true,"tbl":"ai_providers","force":false},{"rls":true,"tbl":"ai_routing_decisions","force":false},{"rls":true,"tbl":"ai_usage_logs","force":false},{"rls":true,"tbl":"ai_usage_quotas","force":false},{"rls":true,"tbl":"analytics_events","force":false},{"rls":true,"tbl":"api_usage","force":false},{"rls":true,"tbl":"attribute_definitions","force":false},{"rls":true,"tbl":"attribute_equivalences","force":false},{"rls":true,"tbl":"attribute_groups","force":false},{"rls":true,"tbl":"audit_log","force":false},{"rls":true,"tbl":"audit_log_gravacao","force":false},{"rls":true,"tbl":"auto_tag_rules","force":false},{"rls":true,"tbl":"bot_detection_log","force":false},{"rls":true,"tbl":"categories","force":false},{"rls":true,"tbl":"category_accessory_categories","force":false},{"rls":true,"tbl":"category_attributes","force":false},{"rls":true,"tbl":"category_colors","force":false},{"rls":true,"tbl":"category_commemorative_dates","force":false},{"rls":true,"tbl":"category_copywriting_config","force":false},{"rls":true,"tbl":"category_relationships","force":false},{"rls":true,"tbl":"category_target_audiences","force":false},{"rls":true,"tbl":"category_variation_types","force":false},{"rls":true,"tbl":"classify_functions_registry","force":false},{"rls":true,"tbl":"collection_products","force":false},{"rls":true,"tbl":"collections","force":false},{"rls":true,"tbl":"color_analysis_staging","force":false},{"rls":true,"tbl":"color_equivalences","force":false},{"rls":true,"tbl":"color_groups","force":false},{"rls":true,"tbl":"color_nuances","force":false},{"rls":true,"tbl":"color_variations","force":false},{"rls":true,"tbl":"commemorative_date_colors","force":false},{"rls":true,"tbl":"commemorative_date_exclusions","force":false},{"rls":true,"tbl":"commemorative_dates","force":false},{"rls":true,"tbl":"company_email_patterns","force":false},{"rls":true,"tbl":"custom_kits","force":false},{"rls":true,"tbl":"discount_approval_requests","force":false},{"rls":true,"tbl":"eco_material_config","force":false},{"rls":true,"tbl":"edge_function_invocations","force":false},{"rls":true,"tbl":"enriched_contacts","force":false},{"rls":true,"tbl":"enrichment_log","force":false},{"rls":true,"tbl":"external_connections_sync_log","force":false},{"rls":true,"tbl":"favorite_items","force":false},{"rls":true,"tbl":"favorite_items_trash","force":false},{"rls":true,"tbl":"favorite_lists","force":false},{"rls":true,"tbl":"feminine_color_config","force":false},{"rls":true,"tbl":"file_scan_logs","force":false},{"rls":true,"tbl":"generated_mockups","force":false},{"rls":true,"tbl":"image_import_log","force":false},{"rls":true,"tbl":"image_types","force":false},{"rls":true,"tbl":"image_validation_log","force":false},{"rls":true,"tbl":"import_pipeline_steps","force":false},{"rls":true,"tbl":"import_staging_images","force":false},{"rls":true,"tbl":"inbound_webhook_endpoints","force":false},{"rls":true,"tbl":"inbound_webhook_events","force":false},{"rls":true,"tbl":"integration_credentials","force":false},{"rls":true,"tbl":"ip_access_control","force":false},{"rls":true,"tbl":"kit_component_print_areas","force":false},{"rls":true,"tbl":"kit_component_types","force":false},{"rls":true,"tbl":"kit_templates","force":false},{"rls":true,"tbl":"login_attempts","force":false},{"rls":true,"tbl":"markup_configurations","force":false},{"rls":true,"tbl":"material_equivalences","force":false},{"rls":true,"tbl":"material_groups","force":false},{"rls":true,"tbl":"material_types","force":false},{"rls":true,"tbl":"material_variations","force":false},{"rls":true,"tbl":"media_assets","force":false},{"rls":true,"tbl":"media_sync_log","force":false},{"rls":true,"tbl":"media_sync_queue","force":false},{"rls":true,"tbl":"mockup_approval_links","force":false},{"rls":true,"tbl":"mockup_credit_transactions","force":false},{"rls":true,"tbl":"mockup_credits","force":false},{"rls":true,"tbl":"mockup_generation_jobs","force":false},{"rls":true,"tbl":"mockup_templates","force":false},{"rls":true,"tbl":"ncm_codes","force":false},{"rls":true,"tbl":"notification_preferences","force":false},{"rls":true,"tbl":"notification_templates","force":false},{"rls":true,"tbl":"notifications","force":false},{"rls":true,"tbl":"order_items","force":false},{"rls":true,"tbl":"orders","force":false},{"rls":true,"tbl":"organizations","force":false},{"rls":true,"tbl":"packaging_compatibility_config","force":false},{"rls":true,"tbl":"packaging_types","force":false},{"rls":true,"tbl":"packagings","force":false},{"rls":true,"tbl":"permissions","force":false},{"rls":true,"tbl":"personalization_techniques","force":false},{"rls":true,"tbl":"price_history","force":false},{"rls":true,"tbl":"print_area_techniques","force":false},{"rls":true,"tbl":"product_ai_history","force":false},{"rls":true,"tbl":"product_category_assignments","force":false},{"rls":true,"tbl":"product_commemorative_dates","force":false},{"rls":true,"tbl":"product_faqs","force":false},{"rls":true,"tbl":"product_images","force":false},{"rls":true,"tbl":"product_included_packagings","force":false},{"rls":true,"tbl":"product_kit_components","force":false},{"rls":true,"tbl":"product_materials","force":false},{"rls":true,"tbl":"product_packaging_compatibility","force":false},{"rls":true,"tbl":"product_packagings","force":false},{"rls":true,"tbl":"product_properties","force":false},{"rls":true,"tbl":"product_relationships","force":false},{"rls":true,"tbl":"product_search_logs","force":false},{"rls":true,"tbl":"product_similarity_group_members","force":false},{"rls":true,"tbl":"product_similarity_groups","force":false},{"rls":true,"tbl":"product_tags","force":false},{"rls":true,"tbl":"product_target_audiences","force":false},{"rls":true,"tbl":"product_variants","force":false},{"rls":true,"tbl":"product_videos","force":false},{"rls":true,"tbl":"products","force":false},{"rls":true,"tbl":"produto_ramo_atividade","force":false},{"rls":true,"tbl":"profiles","force":false},{"rls":true,"tbl":"property_definitions","force":false},{"rls":true,"tbl":"push_subscriptions","force":false},{"rls":true,"tbl":"quote_approval_tokens","force":false},{"rls":true,"tbl":"quote_comments","force":false},{"rls":true,"tbl":"quote_history","force":false},{"rls":true,"tbl":"quote_item_personalizations","force":false},{"rls":true,"tbl":"quote_items","force":false},{"rls":true,"tbl":"quote_templates","force":false},{"rls":true,"tbl":"quote_versions","force":false},{"rls":true,"tbl":"quotes","force":false},{"rls":true,"tbl":"ramo_atividade","force":false},{"rls":true,"tbl":"ramo_atividade_filho","force":false},{"rls":true,"tbl":"role_permissions","force":false},{"rls":true,"tbl":"saved_filters","force":false},{"rls":true,"tbl":"scraper_checkpoints","force":false},{"rls":true,"tbl":"scraper_images_staging","force":false},{"rls":true,"tbl":"search_queries","force":false},{"rls":true,"tbl":"secret_rotation_log","force":false},{"rls":true,"tbl":"seller_discount_limits","force":false},{"rls":true,"tbl":"seo_audit_log","force":false},{"rls":true,"tbl":"seo_redirects","force":false},{"rls":true,"tbl":"sm_images_staging","force":false},{"rls":true,"tbl":"sm_worker_partitions","force":false},{"rls":true,"tbl":"stock_daily_summary","force":false},{"rls":true,"tbl":"stock_snapshots","force":false},{"rls":true,"tbl":"supplier_attribute_definitions","force":false},{"rls":true,"tbl":"supplier_branches","force":false},{"rls":true,"tbl":"supplier_categories","force":false},{"rls":true,"tbl":"supplier_category_mappings","force":false},{"rls":true,"tbl":"supplier_colors","force":false},{"rls":true,"tbl":"supplier_field_mappings","force":false},{"rls":true,"tbl":"supplier_field_priority","force":false},{"rls":true,"tbl":"supplier_image_requirements","force":false},{"rls":true,"tbl":"supplier_image_suffix_mappings","force":false},{"rls":true,"tbl":"supplier_image_suffix_patterns","force":false},{"rls":true,"tbl":"supplier_import_batches","force":false},{"rls":true,"tbl":"supplier_materials","force":false},{"rls":true,"tbl":"supplier_packagings","force":false},{"rls":true,"tbl":"supplier_products_raw","force":false},{"rls":true,"tbl":"supplier_property_mappings","force":false},{"rls":true,"tbl":"supplier_settings","force":false},{"rls":true,"tbl":"supplier_technique_mappings","force":false},{"rls":true,"tbl":"supplier_unit_conversions","force":false},{"rls":true,"tbl":"supplier_value_mappings","force":false},{"rls":true,"tbl":"supplier_video_requirements","force":false},{"rls":true,"tbl":"suppliers","force":false},{"rls":true,"tbl":"system_changelog","force":false},{"rls":true,"tbl":"system_documentation","force":false},{"rls":true,"tbl":"system_settings","force":false},{"rls":true,"tbl":"tabela_preco_gravacao_oficial","force":false},{"rls":true,"tbl":"tabela_preco_gravacao_oficial_faixa","force":false},{"rls":true,"tbl":"tags","force":false},{"rls":true,"tbl":"target_audiences","force":false},{"rls":true,"tbl":"tecnicas_gravacao","force":false},{"rls":true,"tbl":"user_favorites","force":false},{"rls":true,"tbl":"user_filter_presets","force":false},{"rls":true,"tbl":"user_onboarding","force":false},{"rls":true,"tbl":"user_organizations","force":false},{"rls":true,"tbl":"user_roles","force":false},{"rls":true,"tbl":"variant_commemorative_dates","force":false},{"rls":true,"tbl":"variant_supplier_sources","force":false},{"rls":true,"tbl":"variation_types","force":false},{"rls":true,"tbl":"variation_values","force":false},{"rls":true,"tbl":"video_import_queue","force":false},{"rls":true,"tbl":"video_types","force":false},{"rls":true,"tbl":"video_validation_log","force":false},{"rls":true,"tbl":"workspace_notifications","force":false},{"rls":true,"tbl":"xbz_gallery_staging","force":false}]
